guidewd/__init__.py
guidewd/analyze_sitemap.py
guidewd_sitemap_tool-0.1.1.dist-info/LICENSE.txt
guidewd_sitemap_tool-0.1.1.dist-info/METADATA
guidewd_sitemap_tool-0.1.1.dist-info/WHEEL
guidewd_sitemap_tool-0.1.1.dist-info/entry_points.txt
guidewd_sitemap_tool-0.1.1.dist-info/top_level.txt
guidewd_sitemap_tool-0.1.1.dist-info/RECORD
