Metadata-Version: 2.1
Name: guidewd-sitemap-tool
Version: 0.1.1
Summary: Analyze sitemap XML files for SEO optimization with suggestions.
Home-page: https://github.com/KartikeyDhaka/GuideWD/tree/main
Author: Purva Tijare
Author-email: purvat@iiitd.ac.in
Classifier: Programming Language :: Python :: 3
Classifier: License :: OSI Approved :: MIT License
Classifier: Operating System :: OS Independent
Requires-Python: >=3.6
License-File: LICENSE.txt
Requires-Dist: requests
Requires-Dist: beautifulsoup4
Requires-Dist: pandas
